drb/drivers/xml/__init__.py
drb/drivers/xml/_version.py
drb/drivers/xml/factory.py
drb/drivers/xml/node.py
drb/topics/xml/__init__.py
drb/topics/xml/cortex.yml
drb_driver_xml-1.1.1.data/data/requirements.txt
drb_driver_xml-1.1.1.dist-info/LICENCE.txt
drb_driver_xml-1.1.1.dist-info/METADATA
drb_driver_xml-1.1.1.dist-info/WHEEL
drb_driver_xml-1.1.1.dist-info/entry_points.txt
drb_driver_xml-1.1.1.dist-info/top_level.txt
drb_driver_xml-1.1.1.dist-info/RECORD
