Metadata-Version: 2.1
Name: drb-driver-xml
Version: 1.1.1
Summary: DRB XML implementation
Home-page: https://gitlab.com/drb-python/impl/xml
Author: GAEL Systems
Author-email: drb-python@gael.fr
License: UNKNOWN
Project-URL: Documentation, https://drb-python.gitlab.io/impl/xml
Project-URL: Source, https://gitlab.com/drb-python/impl/xml
Platform: UNKNOWN
Classifier: Programming Language :: Python :: 3.8
Classifier: License :: OSI Approved :: GNU Lesser General Public License v3 (LGPLv3)
Classifier: Operating System :: OS Independent
Requires-Python: >=3.8
License-File: LICENCE.txt
Requires-Dist: drb (~=2.0.3)
Requires-Dist: defusedxml (>=0.7.1)
